{
    "id": 20163574,
    "node_id": "MDEwOlJlcG9zaXRvcnkyMDE2MzU3NA==",
    "name": "aioredis",
    "full_name": "aio-libs/aioredis",
    "private": false,
    "owner": {
        "login": "aio-libs",
        "id": 7049303,
        "node_id": "MDEyOk9yZ2FuaXphdGlvbjcwNDkzMDM=",
        "avatar_url": "https://avatars2.githubusercontent.com/u/7049303?v=4",
        "gravatar_id": "",
        "url": "https://api.github.com/users/aio-libs",
        "html_url": "https://github.com/aio-libs",
        "followers_url": "https://api.github.com/users/aio-libs/followers",
        "following_url": "https://api.github.com/users/aio-libs/following{/other_user}",
        "gists_url": "https://api.github.com/users/aio-libs/gists{/gist_id}",
        "starred_url": "https://api.github.com/users/aio-libs/starred{/owner}{/repo}",
        "subscriptions_url": "https://api.github.com/users/aio-libs/subscriptions",
        "organizations_url": "https://api.github.com/users/aio-libs/orgs",
        "repos_url": "https://api.github.com/users/aio-libs/repos",
        "events_url": "https://api.github.com/users/aio-libs/events{/privacy}",
        "received_events_url": "https://api.github.com/users/aio-libs/received_events",
        "type": "Organization",
        "site_admin": false
    },
    "html_url": "https://github.com/aio-libs/aioredis",
    "description": "asyncio (PEP 3156) Redis support",
    "fork": false,
    "url": "https://api.github.com/repos/aio-libs/aioredis",
    "forks_url": "https://api.github.com/repos/aio-libs/aioredis/forks",
    "keys_url": "https://api.github.com/repos/aio-libs/aioredis/keys{/key_id}",
    "collaborators_url": "https://api.github.com/repos/aio-libs/aioredis/collaborators{/collaborator}",
    "teams_url": "https://api.github.com/repos/aio-libs/aioredis/teams",
    "hooks_url": "https://api.github.com/repos/aio-libs/aioredis/hooks",
    "issue_events_url": "https://api.github.com/repos/aio-libs/aioredis/issues/events{/number}",
    "events_url": "https://api.github.com/repos/aio-libs/aioredis/events",
    "assignees_url": "https://api.github.com/repos/aio-libs/aioredis/assignees{/user}",
    "branches_url": "https://api.github.com/repos/aio-libs/aioredis/branches{/branch}",
    "tags_url": "https://api.github.com/repos/aio-libs/aioredis/tags",
    "blobs_url": "https://api.github.com/repos/aio-libs/aioredis/git/blobs{/sha}",
    "git_tags_url": "https://api.github.com/repos/aio-libs/aioredis/git/tags{/sha}",
    "git_refs_url": "https://api.github.com/repos/aio-libs/aioredis/git/refs{/sha}",
    "trees_url": "https://api.github.com/repos/aio-libs/aioredis/git/trees{/sha}",
    "statuses_url": "https://api.github.com/repos/aio-libs/aioredis/statuses/{sha}",
    "languages_url": "https://api.github.com/repos/aio-libs/aioredis/languages",
    "stargazers_url": "https://api.github.com/repos/aio-libs/aioredis/stargazers",
    "contributors_url": "https://api.github.com/repos/aio-libs/aioredis/contributors",
    "subscribers_url": "https://api.github.com/repos/aio-libs/aioredis/subscribers",
    "subscription_url": "https://api.github.com/repos/aio-libs/aioredis/subscription",
    "commits_url": "https://api.github.com/repos/aio-libs/aioredis/commits{/sha}",
    "git_commits_url": "https://api.github.com/repos/aio-libs/aioredis/git/commits{/sha}",
    "comments_url": "https://api.github.com/repos/aio-libs/aioredis/comments{/number}",
    "issue_comment_url": "https://api.github.com/repos/aio-libs/aioredis/issues/comments{/number}",
    "contents_url": "https://api.github.com/repos/aio-libs/aioredis/contents/{+path}",
    "compare_url": "https://api.github.com/repos/aio-libs/aioredis/compare/{base}...{head}",
    "merges_url": "https://api.github.com/repos/aio-libs/aioredis/merges",
    "archive_url": "https://api.github.com/repos/aio-libs/aioredis/{archive_format}{/ref}",
    "downloads_url": "https://api.github.com/repos/aio-libs/aioredis/downloads",
    "issues_url": "https://api.github.com/repos/aio-libs/aioredis/issues{/number}",
    "pulls_url": "https://api.github.com/repos/aio-libs/aioredis/pulls{/number}",
    "milestones_url": "https://api.github.com/repos/aio-libs/aioredis/milestones{/number}",
    "notifications_url": "https://api.github.com/repos/aio-libs/aioredis/notifications{?since,all,participating}",
    "labels_url": "https://api.github.com/repos/aio-libs/aioredis/labels{/name}",
    "releases_url": "https://api.github.com/repos/aio-libs/aioredis/releases{/id}",
    "deployments_url": "https://api.github.com/repos/aio-libs/aioredis/deployments",
    "created_at": "2014-05-25T19:29:57Z",
    "updated_at": "2020-03-05T15:21:25Z",
    "pushed_at": "2020-03-05T14:52:15Z",
    "git_url": "git://github.com/aio-libs/aioredis.git",
    "ssh_url": "git@github.com:aio-libs/aioredis.git",
    "clone_url": "https://github.com/aio-libs/aioredis.git",
    "svn_url": "https://github.com/aio-libs/aioredis",
    "homepage": null,
    "size": 1532,
    "stargazers_count": 1251,
    "watchers_count": 1251,
    "language": "Python",
    "has_issues": true,
    "has_projects": true,
    "has_downloads": true,
    "has_wiki": true,
    "has_pages": false,
    "forks_count": 197,
    "mirror_url": null,
    "archived": false,
    "disabled": false,
    "open_issues_count": 101,
    "license": {
        "key": "mit",
        "name": "MIT License",
        "spdx_id": "MIT",
        "url": "https://api.github.com/licenses/mit",
        "node_id": "MDc6TGljZW5zZTEz"
    },
    "forks": 197,
    "open_issues": 101,
    "watchers": 1251,
    "default_branch": "master",
    "permissions": {
        "admin": false,
        "push": false,
        "pull": true
    },
    "temp_clone_token": "",
    "organization": {
        "login": "aio-libs",
        "id": 7049303,
        "node_id": "MDEyOk9yZ2FuaXphdGlvbjcwNDkzMDM=",
        "avatar_url": "https://avatars2.githubusercontent.com/u/7049303?v=4",
        "gravatar_id": "",
        "url": "https://api.github.com/users/aio-libs",
        "html_url": "https://github.com/aio-libs",
        "followers_url": "https://api.github.com/users/aio-libs/followers",
        "following_url": "https://api.github.com/users/aio-libs/following{/other_user}",
        "gists_url": "https://api.github.com/users/aio-libs/gists{/gist_id}",
        "starred_url": "https://api.github.com/users/aio-libs/starred{/owner}{/repo}",
        "subscriptions_url": "https://api.github.com/users/aio-libs/subscriptions",
        "organizations_url": "https://api.github.com/users/aio-libs/orgs",
        "repos_url": "https://api.github.com/users/aio-libs/repos",
        "events_url": "https://api.github.com/users/aio-libs/events{/privacy}",
        "received_events_url": "https://api.github.com/users/aio-libs/received_events",
        "type": "Organization",
        "site_admin": false
    },
    "network_count": 197,
    "subscribers_count": 38
}