{
    "id": 25367559,
    "node_id": "MDEwOlJlcG9zaXRvcnkyNTM2NzU1OQ==",
    "name": "simian",
    "full_name": "googlearchive/simian",
    "private": false,
    "owner": {
        "login": "googlearchive",
        "id": 12502296,
        "node_id": "MDEyOk9yZ2FuaXphdGlvbjEyNTAyMjk2",
        "avatar_url": "https://avatars2.githubusercontent.com/u/12502296?v=4",
        "gravatar_id": "",
        "url": "https://api.github.com/users/googlearchive",
        "html_url": "https://github.com/googlearchive",
        "followers_url": "https://api.github.com/users/googlearchive/followers",
        "following_url": "https://api.github.com/users/googlearchive/following{/other_user}",
        "gists_url": "https://api.github.com/users/googlearchive/gists{/gist_id}",
        "starred_url": "https://api.github.com/users/googlearchive/starred{/owner}{/repo}",
        "subscriptions_url": "https://api.github.com/users/googlearchive/subscriptions",
        "organizations_url": "https://api.github.com/users/googlearchive/orgs",
        "repos_url": "https://api.github.com/users/googlearchive/repos",
        "events_url": "https://api.github.com/users/googlearchive/events{/privacy}",
        "received_events_url": "https://api.github.com/users/googlearchive/received_events",
        "type": "Organization",
        "site_admin": false
    },
    "html_url": "https://github.com/googlearchive/simian",
    "description": "Simian is an enterprise-class Mac OS X software deployment solution.  Google App Engine hosted server, with a client powered by the Munki open-source project.",
    "fork": false,
    "url": "https://api.github.com/repos/googlearchive/simian",
    "forks_url": "https://api.github.com/repos/googlearchive/simian/forks",
    "keys_url": "https://api.github.com/repos/googlearchive/simian/keys{/key_id}",
    "collaborators_url": "https://api.github.com/repos/googlearchive/simian/collaborators{/collaborator}",
    "teams_url": "https://api.github.com/repos/googlearchive/simian/teams",
    "hooks_url": "https://api.github.com/repos/googlearchive/simian/hooks",
    "issue_events_url": "https://api.github.com/repos/googlearchive/simian/issues/events{/number}",
    "events_url": "https://api.github.com/repos/googlearchive/simian/events",
    "assignees_url": "https://api.github.com/repos/googlearchive/simian/assignees{/user}",
    "branches_url": "https://api.github.com/repos/googlearchive/simian/branches{/branch}",
    "tags_url": "https://api.github.com/repos/googlearchive/simian/tags",
    "blobs_url": "https://api.github.com/repos/googlearchive/simian/git/blobs{/sha}",
    "git_tags_url": "https://api.github.com/repos/googlearchive/simian/git/tags{/sha}",
    "git_refs_url": "https://api.github.com/repos/googlearchive/simian/git/refs{/sha}",
    "trees_url": "https://api.github.com/repos/googlearchive/simian/git/trees{/sha}",
    "statuses_url": "https://api.github.com/repos/googlearchive/simian/statuses/{sha}",
    "languages_url": "https://api.github.com/repos/googlearchive/simian/languages",
    "stargazers_url": "https://api.github.com/repos/googlearchive/simian/stargazers",
    "contributors_url": "https://api.github.com/repos/googlearchive/simian/contributors",
    "subscribers_url": "https://api.github.com/repos/googlearchive/simian/subscribers",
    "subscription_url": "https://api.github.com/repos/googlearchive/simian/subscription",
    "commits_url": "https://api.github.com/repos/googlearchive/simian/commits{/sha}",
    "git_commits_url": "https://api.github.com/repos/googlearchive/simian/git/commits{/sha}",
    "comments_url": "https://api.github.com/repos/googlearchive/simian/comments{/number}",
    "issue_comment_url": "https://api.github.com/repos/googlearchive/simian/issues/comments{/number}",
    "contents_url": "https://api.github.com/repos/googlearchive/simian/contents/{+path}",
    "compare_url": "https://api.github.com/repos/googlearchive/simian/compare/{base}...{head}",
    "merges_url": "https://api.github.com/repos/googlearchive/simian/merges",
    "archive_url": "https://api.github.com/repos/googlearchive/simian/{archive_format}{/ref}",
    "downloads_url": "https://api.github.com/repos/googlearchive/simian/downloads",
    "issues_url": "https://api.github.com/repos/googlearchive/simian/issues{/number}",
    "pulls_url": "https://api.github.com/repos/googlearchive/simian/pulls{/number}",
    "milestones_url": "https://api.github.com/repos/googlearchive/simian/milestones{/number}",
    "notifications_url": "https://api.github.com/repos/googlearchive/simian/notifications{?since,all,participating}",
    "labels_url": "https://api.github.com/repos/googlearchive/simian/labels{/name}",
    "releases_url": "https://api.github.com/repos/googlearchive/simian/releases{/id}",
    "deployments_url": "https://api.github.com/repos/googlearchive/simian/deployments",
    "created_at": "2014-10-17T16:46:00Z",
    "updated_at": "2020-01-29T15:08:41Z",
    "pushed_at": "2019-02-12T20:48:44Z",
    "git_url": "git://github.com/googlearchive/simian.git",
    "ssh_url": "git@github.com:googlearchive/simian.git",
    "clone_url": "https://github.com/googlearchive/simian.git",
    "svn_url": "https://github.com/googlearchive/simian",
    "homepage": "",
    "size": 7492,
    "stargazers_count": 339,
    "watchers_count": 339,
    "language": "Python",
    "has_issues": true,
    "has_projects": true,
    "has_downloads": false,
    "has_wiki": true,
    "has_pages": false,
    "forks_count": 58,
    "mirror_url": null,
    "archived": true,
    "disabled": false,
    "open_issues_count": 32,
    "license": {
        "key": "apache-2.0",
        "name": "Apache License 2.0",
        "spdx_id": "Apache-2.0",
        "url": "https://api.github.com/licenses/apache-2.0",
        "node_id": "MDc6TGljZW5zZTI="
    },
    "forks": 58,
    "open_issues": 32,
    "watchers": 339,
    "default_branch": "master",
    "permissions": {
        "admin": false,
        "push": false,
        "pull": true
    },
    "temp_clone_token": "",
    "organization": {
        "login": "googlearchive",
        "id": 12502296,
        "node_id": "MDEyOk9yZ2FuaXphdGlvbjEyNTAyMjk2",
        "avatar_url": "https://avatars2.githubusercontent.com/u/12502296?v=4",
        "gravatar_id": "",
        "url": "https://api.github.com/users/googlearchive",
        "html_url": "https://github.com/googlearchive",
        "followers_url": "https://api.github.com/users/googlearchive/followers",
        "following_url": "https://api.github.com/users/googlearchive/following{/other_user}",
        "gists_url": "https://api.github.com/users/googlearchive/gists{/gist_id}",
        "starred_url": "https://api.github.com/users/googlearchive/starred{/owner}{/repo}",
        "subscriptions_url": "https://api.github.com/users/googlearchive/subscriptions",
        "organizations_url": "https://api.github.com/users/googlearchive/orgs",
        "repos_url": "https://api.github.com/users/googlearchive/repos",
        "events_url": "https://api.github.com/users/googlearchive/events{/privacy}",
        "received_events_url": "https://api.github.com/users/googlearchive/received_events",
        "type": "Organization",
        "site_admin": false
    },
    "network_count": 58,
    "subscribers_count": 40
}