{
    "id": 4422781,
    "node_id": "MDEwOlJlcG9zaXRvcnk0NDIyNzgx",
    "name": "python-scss",
    "full_name": "pistolero/python-scss",
    "private": false,
    "owner": {
        "login": "pistolero",
        "id": 334124,
        "node_id": "MDQ6VXNlcjMzNDEyNA==",
        "avatar_url": "https://avatars0.githubusercontent.com/u/334124?v=4",
        "gravatar_id": "",
        "url": "https://api.github.com/users/pistolero",
        "html_url": "https://github.com/pistolero",
        "followers_url": "https://api.github.com/users/pistolero/followers",
        "following_url": "https://api.github.com/users/pistolero/following{/other_user}",
        "gists_url": "https://api.github.com/users/pistolero/gists{/gist_id}",
        "starred_url": "https://api.github.com/users/pistolero/starred{/owner}{/repo}",
        "subscriptions_url": "https://api.github.com/users/pistolero/subscriptions",
        "organizations_url": "https://api.github.com/users/pistolero/orgs",
        "repos_url": "https://api.github.com/users/pistolero/repos",
        "events_url": "https://api.github.com/users/pistolero/events{/privacy}",
        "received_events_url": "https://api.github.com/users/pistolero/received_events",
        "type": "User",
        "site_admin": false
    },
    "html_url": "https://github.com/pistolero/python-scss",
    "description": "Python bindings for libsass",
    "fork": false,
    "url": "https://api.github.com/repos/pistolero/python-scss",
    "forks_url": "https://api.github.com/repos/pistolero/python-scss/forks",
    "keys_url": "https://api.github.com/repos/pistolero/python-scss/keys{/key_id}",
    "collaborators_url": "https://api.github.com/repos/pistolero/python-scss/collaborators{/collaborator}",
    "teams_url": "https://api.github.com/repos/pistolero/python-scss/teams",
    "hooks_url": "https://api.github.com/repos/pistolero/python-scss/hooks",
    "issue_events_url": "https://api.github.com/repos/pistolero/python-scss/issues/events{/number}",
    "events_url": "https://api.github.com/repos/pistolero/python-scss/events",
    "assignees_url": "https://api.github.com/repos/pistolero/python-scss/assignees{/user}",
    "branches_url": "https://api.github.com/repos/pistolero/python-scss/branches{/branch}",
    "tags_url": "https://api.github.com/repos/pistolero/python-scss/tags",
    "blobs_url": "https://api.github.com/repos/pistolero/python-scss/git/blobs{/sha}",
    "git_tags_url": "https://api.github.com/repos/pistolero/python-scss/git/tags{/sha}",
    "git_refs_url": "https://api.github.com/repos/pistolero/python-scss/git/refs{/sha}",
    "trees_url": "https://api.github.com/repos/pistolero/python-scss/git/trees{/sha}",
    "statuses_url": "https://api.github.com/repos/pistolero/python-scss/statuses/{sha}",
    "languages_url": "https://api.github.com/repos/pistolero/python-scss/languages",
    "stargazers_url": "https://api.github.com/repos/pistolero/python-scss/stargazers",
    "contributors_url": "https://api.github.com/repos/pistolero/python-scss/contributors",
    "subscribers_url": "https://api.github.com/repos/pistolero/python-scss/subscribers",
    "subscription_url": "https://api.github.com/repos/pistolero/python-scss/subscription",
    "commits_url": "https://api.github.com/repos/pistolero/python-scss/commits{/sha}",
    "git_commits_url": "https://api.github.com/repos/pistolero/python-scss/git/commits{/sha}",
    "comments_url": "https://api.github.com/repos/pistolero/python-scss/comments{/number}",
    "issue_comment_url": "https://api.github.com/repos/pistolero/python-scss/issues/comments{/number}",
    "contents_url": "https://api.github.com/repos/pistolero/python-scss/contents/{+path}",
    "compare_url": "https://api.github.com/repos/pistolero/python-scss/compare/{base}...{head}",
    "merges_url": "https://api.github.com/repos/pistolero/python-scss/merges",
    "archive_url": "https://api.github.com/repos/pistolero/python-scss/{archive_format}{/ref}",
    "downloads_url": "https://api.github.com/repos/pistolero/python-scss/downloads",
    "issues_url": "https://api.github.com/repos/pistolero/python-scss/issues{/number}",
    "pulls_url": "https://api.github.com/repos/pistolero/python-scss/pulls{/number}",
    "milestones_url": "https://api.github.com/repos/pistolero/python-scss/milestones{/number}",
    "notifications_url": "https://api.github.com/repos/pistolero/python-scss/notifications{?since,all,participating}",
    "labels_url": "https://api.github.com/repos/pistolero/python-scss/labels{/name}",
    "releases_url": "https://api.github.com/repos/pistolero/python-scss/releases{/id}",
    "deployments_url": "https://api.github.com/repos/pistolero/python-scss/deployments",
    "created_at": "2012-05-23T16:58:00Z",
    "updated_at": "2019-04-16T13:45:19Z",
    "pushed_at": "2014-09-16T12:41:29Z",
    "git_url": "git://github.com/pistolero/python-scss.git",
    "ssh_url": "git@github.com:pistolero/python-scss.git",
    "clone_url": "https://github.com/pistolero/python-scss.git",
    "svn_url": "https://github.com/pistolero/python-scss",
    "homepage": null,
    "size": 4306,
    "stargazers_count": 94,
    "watchers_count": 94,
    "language": "Python",
    "has_issues": true,
    "has_projects": true,
    "has_downloads": true,
    "has_wiki": true,
    "has_pages": false,
    "forks_count": 10,
    "mirror_url": null,
    "archived": false,
    "disabled": false,
    "open_issues_count": 8,
    "license": {
        "key": "apache-2.0",
        "name": "Apache License 2.0",
        "spdx_id": "Apache-2.0",
        "url": "https://api.github.com/licenses/apache-2.0",
        "node_id": "MDc6TGljZW5zZTI="
    },
    "forks": 10,
    "open_issues": 8,
    "watchers": 94,
    "default_branch": "master",
    "permissions": {
        "admin": false,
        "push": false,
        "pull": true
    },
    "temp_clone_token": "",
    "network_count": 10,
    "subscribers_count": 4
}